TOPSIS_Yashwant/TOPSIS.py
TOPSIS_Yashwant/__init__.py
TOPSIS_Yashwant_101803318-1.0.4.dist-info/LICENSE
TOPSIS_Yashwant_101803318-1.0.4.dist-info/METADATA
TOPSIS_Yashwant_101803318-1.0.4.dist-info/WHEEL
TOPSIS_Yashwant_101803318-1.0.4.dist-info/top_level.txt
TOPSIS_Yashwant_101803318-1.0.4.dist-info/RECORD
