Metadata-Version: 2.1
Name: TOPSIS-Yashwant-101803318
Version: 1.0.4
Summary: A Topsis package that takes inputs as CSV and generates scores in results CSV!
Home-page: https://github.com/meyash/TOPSIS_101803318
Author: Yashwant
Author-email: yashsn2127@gmail.com
License: UNKNOWN
Platform: UNKNOWN
Classifier: Programming Language :: Python :: 3
Classifier: License :: OSI Approved :: MIT License
Classifier: Operating System :: OS Independent
Requires-Dist: numpy (>=1.18.1)
Requires-Dist: pandas (>=1.0.5)
